[
  {
    "id": 1,
    "tournamentRoundText": "1",
    "nextMatchId": 5,
    "name": "TBD",
    "fechaPartido": null,
    "horaPartido": null,
    "jornada": null,
    "myIdMatch": null,
    "participants": [
      "",""
    ]
  },
  {
    "id": 2,
    "tournamentRoundText": "1",
    "nextMatchId": 5,
    "name": "TBD",
    "fechaPartido": null,
    "horaPartido": null,
    "jornada": null,
    "myIdMatch": null,
    "participants": [
      "",""
    ]
  },
  {
    "id": 3,
    "tournamentRoundText": "1",
    "nextMatchId": 6,
    "name": "TBD",
    "fechaPartido": null,
    "horaPartido": null,
    "jornada": null,
    "myIdMatch": null,
    "participants": [
      "",""
    ]
  },
  {
    "id": 4,
    "tournamentRoundText": "1",
    "nextMatchId": 6,
    "name": "TBD",
    "fechaPartido": null,
    "horaPartido": null,
    "jornada": null,
    "myIdMatch": null,
    "participants": [
      "",""
    ]
  },
  {
    "id": 5,
    "tournamentRoundText": "2",
    "nextMatchId": 7,
    "name": "TBD",
    "fechaPartido": null,
    "horaPartido": null,
    "jornada": null,
    "myIdMatch": null,
    "participants": [
      "",""
    ]
  },
  {
    "id": 6,
    "tournamentRoundText": "2",
    "nextMatchId": 7,
    "name": "TBD",
    "fechaPartido": null,
    "horaPartido": null,
    "jornada": null,
    "myIdMatch": null,
    "participants": [
      "",""
    ]
  },
  {
    "id": 7,
    "tournamentRoundText": "3",
    "nextMatchId": null,
    "name": "TBD",
    "fechaPartido": null,
    "horaPartido": null,
    "jornada": null,
    "myIdMatch": null,
    "participants": [
      "",""
    ]
  }
]